karanage_tools/__init__.py
karanage_tools/karanage_system.py
karanage_tools/karanage_tools_state_get.py
karanage_tools/karanage_tools_state_history_get.py
karanage_tools-0.7.3.data/scripts/karanage-system
karanage_tools-0.7.3.data/scripts/karanage-tools-state-get
karanage_tools-0.7.3.data/scripts/karanage-tools-state-history-get
karanage_tools-0.7.3.dist-info/COPYING
karanage_tools-0.7.3.dist-info/METADATA
karanage_tools-0.7.3.dist-info/WHEEL
karanage_tools-0.7.3.dist-info/top_level.txt
karanage_tools-0.7.3.dist-info/RECORD
