Metadata-Version: 2.1
Name: karanage-tools
Version: 0.7.3
Summary: Karanage generic tools
Home-page: https://gitea.atria-soft.org/kangaroo-and-rabbit/karanage
Author: Edouard DUPIN
Author-email: yui.heero@gmail.com
License: MPL-2
Keywords: system cpu status
Classifier: Development Status :: 4 - Beta
Classifier: License :: OSI Approved :: Mozilla Public License 2.0 (MPL 2.0)
Classifier: Programming Language :: Python
Classifier: Operating System :: POSIX
Classifier: Topic :: Software Development :: Libraries
License-File: COPYING
Requires-Dist: karanage (==0.7.3)
